README.md
setup.py
thread_processor/__init__.py
thread_processor.egg-info/PKG-INFO
thread_processor.egg-info/SOURCES.txt
thread_processor.egg-info/dependency_links.txt
thread_processor.egg-info/top_level.txt
thread_processor.egg-info/zip-safe